.gitignore
CHANGES.rst
MANIFEST.in
README.rst
README.txt
bootstrap.py
buildout.cfg
setup.py
test-plone-3.x.cfg
test-plone-4.x.cfg
collective/__init__.py
collective.sharerizer.egg-info/PKG-INFO
collective.sharerizer.egg-info/SOURCES.txt
collective.sharerizer.egg-info/dependency_links.txt
collective.sharerizer.egg-info/entry_points.txt
collective.sharerizer.egg-info/namespace_packages.txt
collective.sharerizer.egg-info/not-zip-safe
collective.sharerizer.egg-info/requires.txt
collective.sharerizer.egg-info/top_level.txt
collective/sharerizer/__init__.py
collective/sharerizer/configure.zcml
collective/sharerizer/interfaces.py
collective/sharerizer/upgrades.py
collective/sharerizer/Extensions/Install.py
collective/sharerizer/Extensions/__init__.py
collective/sharerizer/browser/__init__.py
collective/sharerizer/browser/configlet.py
collective/sharerizer/browser/configure.zcml
collective/sharerizer/browser/document_actions.pt
collective/sharerizer/browser/documentactions.py
collective/sharerizer/profiles/default/browserlayer.xml
collective/sharerizer/profiles/default/controlpanel.xml
collective/sharerizer/profiles/default/metadata.xml
collective/sharerizer/profiles/default/propertiestool.xml
collective/sharerizer/tests/__init__.py
collective/sharerizer/tests/base.py
collective/sharerizer/tests/doctests.txt
collective/sharerizer/tests/test_doctests.py
collective/sharerizer/tests/test_unittests.py
docs/LICENSE.GPL
docs/LICENSE.txt