Metadata-Version: 1.1
Name: collective.sharerizer
Version: 1.4
Summary: A package to inject Web 2.0 style sharing buttons into Plone's document_actions.
Home-page: https://github.com/collective/collective.sharerizer
Author: Groundwire
Author-email: jonb@groundwire.org
License: GPL
Keywords: plone
Platform: UNKNOWN
Classifier: Framework :: Plone
Classifier: Framework :: Plone :: 3.3
Classifier: Framework :: Plone :: 4.0
Classifier: Framework :: Plone :: 4.1
Classifier: Framework :: Plone :: 4.2
Classifier: Framework :: Plone :: 4.3
Classifier: Programming Language :: Python
Classifier: Topic :: Software Development :: Libraries :: Python Modules
